caracal_destruct/__init__.py
caracal_destruct/distribute.py
caracal_destruct/main.py
caracal_destruct/slurm/__init__.py
caracal_destruct/slurm/run.py
caracal_destruct/utils.py
caracal_destruct-0.1.1.dist-info/LICENSE
caracal_destruct-0.1.1.dist-info/METADATA
caracal_destruct-0.1.1.dist-info/WHEEL
caracal_destruct-0.1.1.dist-info/entry_points.txt
caracal_destruct-0.1.1.dist-info/RECORD
