Metadata-Version: 2.1
Name: caracal-destruct
Version: 0.1.1
Summary: Batch runners for CARACal
Home-page: https://github.com/caracal-pipeline/adestruction
License: MIT
Keywords: Astronomy,Slurm,Pipelines
Author: sphemakh
Author-email: sphemakh@gmail.com
Requires-Python: >=3.8,<4.0
Classifier: License :: OSI Approved :: MIT License
Classifier: Programming Language :: Python :: 3
Classifier: Programming Language :: Python :: 3.8
Classifier: Programming Language :: Python :: 3.9
Classifier: Programming Language :: Python :: 3.10
Classifier: Programming Language :: Python :: 3.11
Classifier: Programming Language :: Python :: 3.12
Requires-Dist: caracal[all] (>=1.1.3,<2.0.0)
Requires-Dist: click (>=8.1.3,<9.0.0)
Requires-Dist: omegaconf (>=2.3.0,<3.0.0)
Requires-Dist: simple-slurm (>=0.2.6,<0.3.0)
Requires-Dist: stimela (>=1.7.9,<2.0.0)
Project-URL: Repository, https://github.com/caracal-pipeline/adestruction
